anime_crc/__init__.py
anime_crc/crc.py
anime_crc/management.py
anime_crc-0.9.1.dist-info/AUTHORS.rst
anime_crc-0.9.1.dist-info/LICENSE
anime_crc-0.9.1.dist-info/METADATA
anime_crc-0.9.1.dist-info/WHEEL
anime_crc-0.9.1.dist-info/entry_points.txt
anime_crc-0.9.1.dist-info/top_level.txt
anime_crc-0.9.1.dist-info/RECORD
