Metadata-Version: 2.1
Name: anime-crc
Version: 0.9.1
Summary: Validate and create CRC checksums for files (ex. anime video [ABCD01234].mkv)
Home-page: https://github.com/Nekmo/anime-crc/
Author: Nekmo
Author-email: contacto@nekmo.com
License: UNKNOWN
Download-URL: https://github.com/Nekmo/anime-crc/archive/master.zip
Keywords: anime-crc
Platform: linux
Classifier: License :: OSI Approved :: MIT License
Classifier: Programming Language :: Python :: 3.6
Classifier: Programming Language :: Python :: 3.8
Classifier: Programming Language :: Python :: 3.7
Classifier: Programming Language :: Python :: 3 :: Only
Classifier: Programming Language :: Python :: 3.5
Classifier: Operating System :: POSIX
Classifier: Operating System :: POSIX :: Linux
Classifier: Natural Language :: English
Classifier: Development Status :: 5 - Production/Stable
